[
  {
    "subject": "الفيزياء",
    "grade": "الصف الثالث الثانوي",
    "part": "الجزء الأول",
    "unit": "الوحدة الأولى",
    "lesson": "الدرس 1",
    "title": "الفيزياء الصف الثالث الثانوي - الجزء الأول - الوحدة الأولى - الدرس 1 (كمية التحرك الخطي)",
    "url": "https://www.youtube.com/watch?v=j7bYhY893fw"
  },
  {
    "subject": "الفيزياء",
    "grade": "الصف الثالث الثانوي",
    "part": "الجزء الأول",
    "unit": "الوحدة الأولى",
    "lesson": "الدرس 2",
    "title": "الفيزياء الصف الثالث الثانوي - الجزء الأول - الوحدة الأولى - الدرس 2 (أنواع التصادمات)",
    "url": "https://www.youtube.com/watch?v=1y7ZoGqE0Ag"
  },
  {
    "subject": "الفيزياء",
    "grade": "الصف الثالث الثانوي",
    "part": "الجزء الأول",
    "unit": "الوحدة الأولى",
    "lesson": "الدرس 3",
    "title": "الفيزياء الصف الثالث الثانوي - الجزء الأول - الوحدة الأولى - الدرس 3 (حل تمارين على كمية التحرك والتصادم)",
    "url": "https://www.youtube.com/watch?v=J8np9y5OvW8"
  },
  {
    "subject": "الفيزياء",
    "grade": "الصف الثالث الثانوي",
    "part": "الجزء الأول",
    "unit": "الوحدة الأولى",
    "lesson": "الدرس 4",
    "title": "الفيزياء الصف الثالث الثانوي - الجزء الأول - الوحدة الأولى - الدرس 4 (الصواريخ ذاتية الدفع)",
    "url": "https://www.youtube.com/watch?v=Y3fLXlcaKzQ"
  },
  {
    "subject": "الفيزياء",
    "grade": "الصف الثالث الثانوي",
    "part": "الجزء الأول",
    "unit": "الوحدة الأولى",
    "lesson": "الدرس 5",
    "title": "الفيزياء الصف الثالث الثانوي - الجزء الأول - الوحدة الأولى - الدرس 5 (حل تمارين على الصواريخ ذاتية الدفع)",
    "url": "https://www.youtube.com/watch?v=Y7d5rCU8QLg"
  },
  {
    "subject": "الفيزياء",
    "grade": "الصف الثالث الثانوي",
    "part": "الجزء الأول",
    "unit": "الوحدة الأولى",
    "lesson": "الدرس 6",
    "title": "الفيزياء الصف الثالث الثانوي - الجزء الأول - الوحدة الأولى - الدرس 6 (سرعة الإفلات من الجاذبية)",
    "url": "https://www.youtube.com/watch?v=tVt69kUBaXY"
  },
  {
    "subject": "الفيزياء",
    "grade": "الصف الثالث الثانوي",
    "part": "الجزء الأول",
    "unit": "الوحدة الأولى",
    "lesson": "الدرس 7",
    "title": "الفيزياء الصف الثالث الثانوي - الجزء الأول - الوحدة الأولى - الدرس 7 (حساب سرعة الإفلات من الجاذبية)",
    "url": "https://www.youtube.com/watch?v=ucXSVEqQOTc"
  },
  {
    "subject": "الفيزياء",
    "grade": "الصف الثالث الثانوي",
    "part": "الجزء الأول",
    "unit": "الوحدة الأولى",
    "lesson": "الدرس 8",
    "title": "الفيزياء الصف الثالث الثانوي - الجزء الأول - الوحدة الأولى - الدرس 8 (حركة الأقمار الصناعية حول الأرض)",
    "url": "https://www.youtube.com/watch?v=zjHGT29Lf0Q"
  },
  {
    "subject": "الفيزياء",
    "grade": "الصف الثالث الثانوي",
    "part": "الجزء الأول",
    "unit": "الوحدة الأولى",
    "lesson": "الدرس 9",
    "title": "الفيزياء الصف الثالث الثانوي - الجزء الأول - الوحدة الأولى - الدرس 9 (حساب سرعة القمر الصناعي)",
    "url": "https://www.youtube.com/watch?v=TpORA9dojNE"
  },
  {
    "subject": "الفيزياء",
    "grade": "الصف الثالث الثانوي",
    "part": "الجزء الأول",
    "unit": "الوحدة الأولى",
    "lesson": "الدرس 10",
    "title": "الفيزياء الصف الثالث الثانوي - الجزء الأول - الوحدة الأولى - الدرس 10 (كمية التحرك الزاوي)",
    "url": "https://www.youtube.com/watch?v=vqmiOm95t4I"
  },
  {
    "subject": "الفيزياء",
    "grade": "الصف الثالث الثانوي",
    "part": "الجزء الأول",
    "unit": "الوحدة الأولى",
    "lesson": "الدرس 11",
    "title": "الفيزياء الصف الثالث الثانوي - الجزء الأول - الوحدة الأولى - الدرس 11 (حركة المقذوفات)",
    "url": "https://www.youtube.com/watch?v=6HOmyY7lkBU"
  },
  {
    "subject": "الفيزياء",
    "grade": "الصف الثالث الثانوي",
    "part": "الجزء الأول",
    "unit": "الوحدة الأولى",
    "lesson": "الدرس 12",
    "title": "الفيزياء الصف الثالث الثانوي - الجزء الأول - الوحدة الأولى - الدرس 12 (جميع تعريفات الوحدة الأولى)",
    "url": "https://www.youtube.com/watch?v=x35ImtuZ7Eg"
  }
]
